pwntools_util/__init__.py
pwntools_util/util/string_getter.py
pwntools_util/util/text_colors.py
pwntools_util/util/type_convert.py
pwntools_util-0.2.3.dist-info/licenses/LICENSE
pwntools_util-0.2.3.dist-info/METADATA
pwntools_util-0.2.3.dist-info/WHEEL
pwntools_util-0.2.3.dist-info/top_level.txt
pwntools_util-0.2.3.dist-info/RECORD
