Metadata-Version: 2.4
Name: pwntools_util
Version: 0.2.3
Summary: pwntools wrapper with quality-of-life and common utils
Author-email: Mario Chao <az0112mario@gmail.com>
License-Expression: MIT
Project-URL: Homepage, https://github.com/MarioChao/pwntools_util
Project-URL: Issues, https://github.com/MarioChao/pwntools_util/issues
Keywords: pwntools,exploit,ctf,flag
Classifier: Programming Language :: Python :: 3
Requires-Python: >=3.6
License-File: LICENSE
Requires-Dist: pwntools>=4.14.1
Dynamic: license-file
